saml2_mdq/__init__.py
saml2_mdq/admin.py
saml2_mdq/apps.py
saml2_mdq/models.py
saml2_mdq/tests.py
saml2_mdq/urls.py
saml2_mdq/utils.py
saml2_mdq/views.py
saml2_mdq-0.6.5.dist-info/METADATA
saml2_mdq-0.6.5.dist-info/RECORD
saml2_mdq-0.6.5.dist-info/WHEEL
saml2_mdq-0.6.5.dist-info/top_level.txt
