Metadata-Version: 2.1
Name: saml2-mdq
Version: 0.6.5
Summary: Django SAML MDQ
Home-page: https://github.com/UniversitaDellaCalabria/Django-MDQ
Author: Giuseppe De Marco
Author-email: giuseppe.demarco@unical.it
License: BSD
Platform: UNKNOWN
Classifier: Development Status :: 5 - Production/Stable
Classifier: License :: OSI Approved :: BSD License
Classifier: Programming Language :: Python :: 2
Classifier: Programming Language :: Python :: 3
Requires-Dist: django
Requires-Dist: pyff
